MANIFEST.in
setup.py
docs/CONTRIBUTORS.txt
docs/HISTORY.txt
docs/LICENSE.ZPL
docs/LICENSE.txt
docs/README.txt
src/ztfy/__init__.py
src/ztfy.zmq.egg-info/PKG-INFO
src/ztfy.zmq.egg-info/SOURCES.txt
src/ztfy.zmq.egg-info/dependency_links.txt
src/ztfy.zmq.egg-info/entry_points.txt
src/ztfy.zmq.egg-info/namespace_packages.txt
src/ztfy.zmq.egg-info/not-zip-safe
src/ztfy.zmq.egg-info/requires.txt
src/ztfy.zmq.egg-info/top_level.txt
src/ztfy/zmq/__init__.py
src/ztfy/zmq/configure.zcml
src/ztfy/zmq/handler.py
src/ztfy/zmq/interfaces.py
src/ztfy/zmq/process.py
src/ztfy/zmq/socket.py
src/ztfy/zmq/doctests/README.txt
src/ztfy/zmq/locales/ztfy.zmq.pot
src/ztfy/zmq/locales/en/LC_MESSAGES/ztfy.zmq.mo
src/ztfy/zmq/locales/en/LC_MESSAGES/ztfy.zmq.po
src/ztfy/zmq/locales/fr/LC_MESSAGES/ztfy.zmq.mo
src/ztfy/zmq/locales/fr/LC_MESSAGES/ztfy.zmq.po
src/ztfy/zmq/tests/__init__.py
src/ztfy/zmq/tests/test_docs.py
src/ztfy/zmq/tests/test_docstrings.py