Metadata-Version: 1.1
Name: ztfy.zmq
Version: 0.1.4
Summary: ZTFY integration of ZeroMQ library
Home-page: http://hg.ztfy.org/ztfy.zmq
Author: Thierry Florac
Author-email: tflorac@ulthar.net
License: zpl
Keywords: ZTFY zmq ZeroMQ 0MQ
Platform: UNKNOWN
Classifier: Programming Language :: Python
